
{"items":[{"name":"Getting Started","href":"GettingStarted/index.html","tocHref":"GettingStarted/toc.html","topicHref":"GettingStarted/index.html"},{"name":"Docs","href":"api/index.html","tocHref":"api/toc.html","topicHref":"api/index.html","homepage":"api/index.html"},{"name":"Release Notes","href":"ReleaseNotes.html","topicHref":"ReleaseNotes.html"},{"name":"Test Coverage","href":"TestCoverage.html","topicHref":"TestCoverage.html"},{"name":"Realistic Example","href":"RealisticExample/index.html","tocHref":"RealisticExample/toc.html","topicHref":"RealisticExample/index.html","homepage":"RealisticExample/index.html"}]}
